phasor_handler/__init__.py
phasor_handler/app.py
phasor_handler/img/logo.ico
phasor_handler/img/icons/chevron-down.svg
phasor_handler/img/icons/chevron-up.svg
phasor_handler/models/dir_manager.py
phasor_handler/scripts/contrast.py
phasor_handler/scripts/convert.py
phasor_handler/scripts/meta_reader.py
phasor_handler/scripts/plot.py
phasor_handler/scripts/register.py
phasor_handler/themes/__init__.py
phasor_handler/themes/dark_theme.py
phasor_handler/tools/__init__.py
phasor_handler/tools/check_stylesheet.py
phasor_handler/tools/misc.py
phasor_handler/widgets/__init__.py
phasor_handler/widgets/analysis/view.py
phasor_handler/widgets/analysis/components/__init__.py
phasor_handler/widgets/analysis/components/bnc.py
phasor_handler/widgets/analysis/components/circle_roi.py
phasor_handler/widgets/analysis/components/image_view.py
phasor_handler/widgets/analysis/components/meta_info.py
phasor_handler/widgets/analysis/components/roi_list.py
phasor_handler/widgets/analysis/components/trace_plot.py
phasor_handler/widgets/conversion/view.py
phasor_handler/widgets/registration/view.py
phasor_handler/widgets/secondlevel/view.py
phasor_handler/workers/__init__.py
phasor_handler/workers/analysis_worker.py
phasor_handler/workers/conversion_worker.py
phasor_handler/workers/histogram_worker.py
phasor_handler/workers/registration_worker.py
phasor_handler/workers/secondlevel_worker.py
phasor_handler-3.0.0.dist-info/licenses/LICENSE.md
phasor_handler-3.0.0.dist-info/METADATA
phasor_handler-3.0.0.dist-info/WHEEL
phasor_handler-3.0.0.dist-info/entry_points.txt
phasor_handler-3.0.0.dist-info/top_level.txt
phasor_handler-3.0.0.dist-info/RECORD
