Metadata-Version: 2.4
Name: phasor-handler
Version: 3.0.0
Summary: A PyQt6 GUI toolbox for processing two-photon phasor imaging data
Author-email: Josia Shemuel <joshemuel@users.noreply.github.com>
License: MIT License
Project-URL: Homepage, https://github.com/joshemuel/Phasor-Handler
Project-URL: Repository, https://github.com/joshemuel/Phasor-Handler
Project-URL: Issues, https://github.com/joshemuel/Phasor-Handler/issues
Keywords: two-photon,phasor,imaging,calcium,neuroscience,suite2p
Classifier: Development Status :: 4 - Beta
Classifier: Intended Audience :: Science/Research
Classifier: Topic :: Scientific/Engineering :: Bio-Informatics
Classifier: Topic :: Scientific/Engineering :: Image Processing
Classifier: License :: OSI Approved :: MIT License
Classifier: Programming Language :: Python :: 3
Classifier: Programming Language :: Python :: 3.9
Classifier: Operating System :: Microsoft :: Windows
Classifier: Environment :: X11 Applications :: Qt
Requires-Python: <3.10,>=3.9.23
License-File: LICENSE.md
Requires-Dist: PyQt6>=6.4.0
Requires-Dist: numpy<2.0.0,>=1.21.0
Requires-Dist: matplotlib>=3.5.0
Requires-Dist: tifffile>=2021.11.2
Requires-Dist: pyyaml>=6.0
Requires-Dist: suite2p>=0.14.0
Requires-Dist: pyqtdarktheme>=1.0.0
Requires-Dist: Pillow>=9.0.0
Requires-Dist: scikit-image>=0.19.0
Requires-Dist: scipy>=1.7.0
Requires-Dist: npTDMS>=1.2.0
Requires-Dist: pandas>=1.3.0
Provides-Extra: dev
Requires-Dist: pytest>=7.0.0; extra == "dev"
Requires-Dist: black>=22.0.0; extra == "dev"
Requires-Dist: flake8>=4.0.0; extra == "dev"
Dynamic: license-file
